__builtins__.py
everysk/__init__.py
everysk/config.py
everysk/config.pyi
everysk/settings.py
everysk/tests.py
everysk/utils.py
everysk/core/compress.py
everysk/core/exceptions.py
everysk/core/fields.py
everysk/core/firestore.py
everysk/core/http.py
everysk/core/log.py
everysk/core/number.py
everysk/core/object.py
everysk/core/redis.py
everysk/core/slack.py
everysk/core/string.py
everysk/core/tests.py
everysk/core/threads.py
everysk/core/undefined.py
everysk/core/workers.py
everysk/core/_tests/__init__.py
everysk/core/_tests/compress.py
everysk/core/_tests/config.py
everysk/core/_tests/exceptions.py
everysk/core/_tests/fields.py
everysk/core/_tests/firestore.py
everysk/core/_tests/http.py
everysk/core/_tests/log.py
everysk/core/_tests/number.py
everysk/core/_tests/object.py
everysk/core/_tests/redis.py
everysk/core/_tests/slack.py
everysk/core/_tests/string.py
everysk/core/_tests/threads.py
everysk/core/_tests/undefined.py
everysk/core/_tests/utils.py
everysk/core/_tests/workers.py
everysk/core/cloud_function/main.py
everysk/core/cloud_function/tests.py
everysk/core/datetime/__init__.py
everysk/core/datetime/calendar.py
everysk/core/datetime/date.py
everysk/core/datetime/date_mixin.py
everysk/core/datetime/date_settings.py
everysk/core/datetime/datetime.py
everysk/core/datetime/tests/calendar.py
everysk/core/datetime/tests/date.py
everysk/core/datetime/tests/date_mixin.py
everysk/core/datetime/tests/datetime.py
everysk/core/fixtures/_settings.py
everysk/core/fixtures/other/_settings.py
everysk/sdk/base.py
everysk/sdk/settings.py
everysk/sdk/tests.py
everysk/sdk/_tests/base.py
everysk/sdk/engines/cryptography.py
everysk/sdk/engines/_tests/cryptography.py
everysk/sdk/entities/base.py
everysk/sdk/entities/base_list.py
everysk/sdk/entities/fields.py
everysk/sdk/entities/query.py
everysk/sdk/entities/script.py
everysk/sdk/entities/settings.py
everysk/sdk/entities/tags.py
everysk/sdk/entities/_tests/base.py
everysk/sdk/entities/_tests/base_list.py
beta_everysk_lib-1.3.656.dist-info/LICENSE.txt
beta_everysk_lib-1.3.656.dist-info/METADATA
beta_everysk_lib-1.3.656.dist-info/WHEEL
beta_everysk_lib-1.3.656.dist-info/top_level.txt
beta_everysk_lib-1.3.656.dist-info/RECORD
