Metadata-Version: 2.1
Name: beta-everysk-lib
Version: 1.3.656
Summary: Generic lib to share python code on Everysk.
License: (C) Copyright 2023 EVERYSK TECHNOLOGIES
Keywords: python,setuptools,development,lib
Requires-Python: >=3.11
License-File: LICENSE.txt
Requires-Dist: python-dateutil ==2.8.2
Requires-Dist: holidays ==0.32
Requires-Dist: tzdata ==2024.1
Provides-Extra: firestore
Requires-Dist: certifi ==2024.2.2 ; extra == 'firestore'
Requires-Dist: charset-normalizer ==3.3.2 ; extra == 'firestore'
Requires-Dist: idna ==3.6 ; extra == 'firestore'
Requires-Dist: urllib3 ==2.2.1 ; extra == 'firestore'
Requires-Dist: requests ==2.31.0 ; extra == 'firestore'
Requires-Dist: pyasn1 ==0.5.1 ; extra == 'firestore'
Requires-Dist: pyasn1-modules ==0.3.0 ; extra == 'firestore'
Requires-Dist: cachetools ==5.3.2 ; extra == 'firestore'
Requires-Dist: rsa ==4.9 ; extra == 'firestore'
Requires-Dist: google-auth ==2.28.1 ; extra == 'firestore'
Requires-Dist: googleapis-common-protos ==1.62.0 ; extra == 'firestore'
Requires-Dist: grpcio ==1.60.1 ; extra == 'firestore'
Requires-Dist: grpcio-status ==1.60.1 ; extra == 'firestore'
Requires-Dist: google-api-core[grpc] ==2.17.1 ; extra == 'firestore'
Requires-Dist: google-cloud-core ==2.4.1 ; extra == 'firestore'
Requires-Dist: proto-plus ==1.23.0 ; extra == 'firestore'
Requires-Dist: protobuf ==4.25.3 ; extra == 'firestore'
Requires-Dist: google-cloud-firestore ==2.15.0 ; extra == 'firestore'
Provides-Extra: gcp_log
Requires-Dist: certifi ==2024.2.2 ; extra == 'gcp_log'
Requires-Dist: charset-normalizer ==3.3.2 ; extra == 'gcp_log'
Requires-Dist: idna ==3.6 ; extra == 'gcp_log'
Requires-Dist: urllib3 ==2.2.1 ; extra == 'gcp_log'
Requires-Dist: requests ==2.31.0 ; extra == 'gcp_log'
Requires-Dist: pyasn1 ==0.5.1 ; extra == 'gcp_log'
Requires-Dist: pyasn1-modules ==0.3.0 ; extra == 'gcp_log'
Requires-Dist: cachetools ==5.3.2 ; extra == 'gcp_log'
Requires-Dist: rsa ==4.9 ; extra == 'gcp_log'
Requires-Dist: google-auth ==2.28.1 ; extra == 'gcp_log'
Requires-Dist: googleapis-common-protos ==1.62.0 ; extra == 'gcp_log'
Requires-Dist: grpcio ==1.60.1 ; extra == 'gcp_log'
Requires-Dist: grpcio-status ==1.60.1 ; extra == 'gcp_log'
Requires-Dist: google-api-core[grpc] ==2.17.1 ; extra == 'gcp_log'
Requires-Dist: google-cloud-core ==2.4.1 ; extra == 'gcp_log'
Requires-Dist: proto-plus ==1.23.0 ; extra == 'gcp_log'
Requires-Dist: protobuf ==4.25.3 ; extra == 'gcp_log'
Requires-Dist: grpc-google-iam-v1 ==0.13.0 ; extra == 'gcp_log'
Requires-Dist: google-cloud-appengine-logging ==1.4.1 ; extra == 'gcp_log'
Requires-Dist: google-cloud-audit-log ==0.2.5 ; extra == 'gcp_log'
Requires-Dist: google-cloud-logging ==3.9.0 ; extra == 'gcp_log'
Provides-Extra: redis
Requires-Dist: redis ==5.0.1 ; extra == 'redis'
Provides-Extra: requests
Requires-Dist: certifi ==2024.2.2 ; extra == 'requests'
Requires-Dist: charset-normalizer ==3.3.2 ; extra == 'requests'
Requires-Dist: idna ==3.6 ; extra == 'requests'
Requires-Dist: urllib3 ==2.2.1 ; extra == 'requests'
Requires-Dist: requests ==2.31.0 ; extra == 'requests'
Provides-Extra: tasks
Requires-Dist: certifi ==2024.2.2 ; extra == 'tasks'
Requires-Dist: charset-normalizer ==3.3.2 ; extra == 'tasks'
Requires-Dist: idna ==3.6 ; extra == 'tasks'
Requires-Dist: urllib3 ==2.2.1 ; extra == 'tasks'
Requires-Dist: requests ==2.31.0 ; extra == 'tasks'
Requires-Dist: pyasn1 ==0.5.1 ; extra == 'tasks'
Requires-Dist: pyasn1-modules ==0.3.0 ; extra == 'tasks'
Requires-Dist: cachetools ==5.3.2 ; extra == 'tasks'
Requires-Dist: rsa ==4.9 ; extra == 'tasks'
Requires-Dist: google-auth ==2.28.1 ; extra == 'tasks'
Requires-Dist: googleapis-common-protos ==1.62.0 ; extra == 'tasks'
Requires-Dist: grpcio ==1.60.1 ; extra == 'tasks'
Requires-Dist: grpcio-status ==1.60.1 ; extra == 'tasks'
Requires-Dist: google-api-core[grpc] ==2.17.1 ; extra == 'tasks'
Requires-Dist: google-cloud-core ==2.4.1 ; extra == 'tasks'
Requires-Dist: proto-plus ==1.23.0 ; extra == 'tasks'
Requires-Dist: protobuf ==4.25.3 ; extra == 'tasks'
Requires-Dist: grpc-google-iam-v1 ==0.13.0 ; extra == 'tasks'
Requires-Dist: google-cloud-tasks ==2.16.1 ; extra == 'tasks'
